pyphene/__init__.py
pyphene/graph.py
pyphene/node.py
pyphene-1.0.10.dist-info/LICENSE.txt
pyphene-1.0.10.dist-info/METADATA
pyphene-1.0.10.dist-info/WHEEL
pyphene-1.0.10.dist-info/top_level.txt
pyphene-1.0.10.dist-info/RECORD
