Metadata-Version: 2.1
Name: pyphene
Version: 1.0.10
Summary: A multithreaded graph runner
Home-page: https://github.com/movinglake/pyphene.git
Author: Andres Paez
Author-email: andres@movinglake.com
Project-URL: repository, https://github.com/movinglake/pyphene.git
Classifier: Programming Language :: Python :: 3
Classifier: License :: OSI Approved :: MIT License
Classifier: Operating System :: OS Independent
Requires-Python: >=3.6
License-File: LICENSE.txt
